folders/__init__.py
folders/folders.py
Folders-0.0.8.dist-info/LICENSE
Folders-0.0.8.dist-info/METADATA
Folders-0.0.8.dist-info/WHEEL
Folders-0.0.8.dist-info/entry_points.txt
Folders-0.0.8.dist-info/top_level.txt
Folders-0.0.8.dist-info/RECORD
