Metadata-Version: 2.1
Name: Folders
Version: 0.0.8
Summary: Implementation of the Folders📂 esoteric programming language, a language with no code and just folders.
Home-page: https://github.com/SinaKhalili/Folders.py
Author: Sina Khalili
Author-email: khalili@sfu.ca
License: UNKNOWN
Platform: UNKNOWN
Classifier: License :: OSI Approved :: MIT License
Classifier: Operating System :: OS Independent
Classifier: Programming Language :: Python
License-File: LICENSE
